6-bit Counter/design.sv
// Code your design here

module counter(
  input CLK,
  input RST,
  output reg [5:0] count
);
  
  always @ (posedge CLK)
    begin
      if (RST == 1)
        begin
          // RST High sets counter to 0
          count <= 0;
        end
      else
        begin
          count <= count + 1;
        end
    end
  
endmodule

6-bit Counter/testbench.sv
// Code your testbench here
// or browse Examples

module tb();
  integer counter;
  reg CLK;
  reg RST;
  wire [5:0] OUT;
  
  counter count0(CLK, RST, OUT);
  
  // Initialise Registers
  initial begin
    //creating a file to store simulation waveform data
    $dumpfile("dump.vcd");
    //dump the waveform data to the file
    $dumpvars(1, tb);
    
    // Counter to determine simulation stop
    counter = 0;
    // Initialise Clock as 0 (LOW signal)
    CLK = 1'b0;
    
    // RST is pulsed once to reset counter to 0
    RST = 1;
    RST <= 0;
  end

  // Runs indefinitely
  always
    begin
      // Pulsing of CLK
      CLK = 1'b1; 
      #20; // high for 20 * timescale = 20 ns

      CLK = 1'b0;
      #20; // low for 20 * timescale = 20 ns
    end    
  
  // Execute input and processing at positive edge of CLK
  always @(posedge CLK)
    begin
      RST <= 0;
      
      counter = counter + 1;

      $display("============================");
      $display("OUT = %b or %d", OUT, OUT);

      // After 68 input entries, end simulation
      // Exceeding counter limit to demonstrate overflow
      if (counter == 68)
        begin
          $finish;
        end
    end
endmodule

6-bit Counter/dump.vcd
$date
	Thu Jun 24 14:29:42 2021
$end
$version
	Icarus Verilog
$end
$timescale
	1s
$end
$scope module tb $end
$var wire 6 ! OUT [5:0] $end
$var reg 1 " CLK $end
$var reg 1 # RST $end
$var integer 32 $ counter [31:0] $end
$upscope $end
$enddefinitions $end
#0
$dumpvars
b0 $
0#
1"
b0 !
$end
#20
0"
#40
b1 !
b1 $
1"
#60
0"
#80
b10 !
b10 $
1"
#100
0"
#120
b11 !
b11 $
1"
#140
0"
#160
b100 !
b100 $
1"
#180
0"
#200
b101 !
b101 $
1"
#220
0"
#240
b110 !
b110 $
1"
#260
0"
#280
b111 !
b111 $
1"
#300
0"
#320
b1000 !
b1000 $
1"
#340
0"
#360
b1001 !
b1001 $
1"
#380
0"
#400
b1010 !
b1010 $
1"
#420
0"
#440
b1011 !
b1011 $
1"
#460
0"
#480
b1100 !
b1100 $
1"
#500
0"
#520
b1101 !
b1101 $
1"
#540
0"
#560
b1110 !
b1110 $
1"
#580
0"
#600
b1111 !
b1111 $
1"
#620
0"
#640
b10000 !
b10000 $
1"
#660
0"
#680
b10001 !
b10001 $
1"
#700
0"
#720
b10010 !
b10010 $
1"
#740
0"
#760
b10011 !
b10011 $
1"
#780
0"
#800
b10100 !
b10100 $
1"
#820
0"
#840
b10101 !
b10101 $
1"
#860
0"
#880
b10110 !
b10110 $
1"
#900
0"
#920
b10111 !
b10111 $
1"
#940
0"
#960
b11000 !
b11000 $
1"
#980
0"
#1000
b11001 !
b11001 $
1"
#1020
0"
#1040
b11010 !
b11010 $
1"
#1060
0"
#1080
b11011 !
b11011 $
1"
#1100
0"
#1120
b11100 !
b11100 $
1"
#1140
0"
#1160
b11101 !
b11101 $
1"
#1180
0"
#1200
b11110 !
b11110 $
1"
#1220
0"
#1240
b11111 !
b11111 $
1"
#1260
0"
#1280
b100000 !
b100000 $
1"
#1300
0"
#1320
b100001 !
b100001 $
1"
#1340
0"
#1360
b100010 !
b100010 $
1"
#1380
0"
#1400
b100011 !
b100011 $
1"
#1420
0"
#1440
b100100 !
b100100 $
1"
#1460
0"
#1480
b100101 !
b100101 $
1"
#1500
0"
#1520
b100110 !
b100110 $
1"
#1540
0"
#1560
b100111 !
b100111 $
1"
#1580
0"
#1600
b101000 !
b101000 $
1"
#1620
0"
#1640
b101001 !
b101001 $
1"
#1660
0"
#1680
b101010 !
b101010 $
1"
#1700
0"
#1720
b101011 !
b101011 $
1"
#1740
0"
#1760
b101100 !
b101100 $
1"
#1780
0"
#1800
b101101 !
b101101 $
1"
#1820
0"
#1840
b101110 !
b101110 $
1"
#1860
0"
#1880
b101111 !
b101111 $
1"
#1900
0"
#1920
b110000 !
b110000 $
1"
#1940
0"
#1960
b110001 !
b110001 $
1"
#1980
0"
#2000
b110010 !
b110010 $
1"
#2020
0"
#2040
b110011 !
b110011 $
1"
#2060
0"
#2080
b110100 !
b110100 $
1"
#2100
0"
#2120
b110101 !
b110101 $
1"
#2140
0"
#2160
b110110 !
b110110 $
1"
#2180
0"
#2200
b110111 !
b110111 $
1"
#2220
0"
#2240
b111000 !
b111000 $
1"
#2260
0"
#2280
b111001 !
b111001 $
1"
#2300
0"
#2320
b111010 !
b111010 $
1"
#2340
0"
#2360
b111011 !
b111011 $
1"
#2380
0"
#2400
b111100 !
b111100 $
1"
#2420
0"
#2440
b111101 !
b111101 $
1"
#2460
0"
#2480
b111110 !
b111110 $
1"
#2500
0"
#2520
b111111 !
b111111 $
1"
#2540
0"
#2560
b0 !
b1000000 $
1"
#2580
0"
#2600
b1 !
b1000001 $
1"
#2620
0"
#2640
b10 !
b1000010 $
1"
#2660
0"
#2680
b11 !
b1000011 $
1"
#2700
0"
#2720
b100 !
b1000100 $
1"
