MemoryRead_v2.0/design.sv
// Code your design here

module counter(
  input CLK,
  input RST,
  output reg [5:0] count
);
  
  always @ (posedge CLK)
    begin
      if (RST == 1)
        begin
          count <= 0;
        end
      else if (RST == 0)
        begin
          count <= count + 1;
        end
    end
  
endmodule

module memory(
  input CLK,
  input RST,
  input [5:0] ADD,
  output reg CLR,
  output reg [5:0] DATA
);

  reg DELAY = 0;
  // Introduce 2 stall registers to delay 2 clock cycles
  reg STALLONE = 0;
  reg STALLTWO = 0;
  wire [5:0] countADD;
  
  counter count0(CLK, RST, countADD);
  
  always @(posedge CLK)
    begin
      // When DELAY initiated, initialise second stall
      if (DELAY == 1)
        begin
          STALLTWO <= 1;
        end
      if (STALLTWO == 1)
        begin
          // When STALLTWO reached, reset registers to 0
          DELAY <= 0;
          STALLONE <= 0;
          STALLTWO <= 0;
        end
      CLR <= 1;
      DATA <= 63;
      // Check if there's no stall
      if ((ADD == countADD) && (STALLONE == 0))
        begin
          DATA <= countADD;
          CLR <= 0;
          // Start the Delay sequence
          DELAY <= 1;
          // First stall begins
          STALLONE <= 1;
        end
    end
  
endmodule

MemoryRead_v2.0/testbench.sv
// Code your testbench here
// or browse Examples

`timescale 1 ns/10 ps  // time-unit = 1 ns, precision = 10 ps

module tb();
  integer counter;
  reg CLK;
  reg RST;
  reg [5:0] ADD;
  wire CLR;
  wire [5:0] OUT;
  wire [5:0] COUNTADD;
  
  memory memory0(CLK, RST, ADD, CLR, OUT);
  counter counter0(CLK, RST, COUNTADD);
  
  // Initialise Registers
  initial begin
    //creating a file to store simulation waveform data
    $dumpfile("dump.vcd");
    //dump the waveform data to the file
    $dumpvars(1, tb);
    
    // Counter to determine simulation stop
    counter = 0;
    // Initialise Clock as 0 (LOW signal)
    CLK = 1'b0;
    
    // RST is pulsed once to reset counter to 0
    RST = 1;
    RST <= 0;
    
    // Initialise Address to be called as 5
    ADD <= 5;
  end

  // Runs indefinitely
  always
    begin
      // Pulsing of CLK
      CLK = 1'b1; 
      #20; // high for 20 * timescale = 20 ns

      CLK = 1'b0;
      #20; // low for 20 * timescale = 20 ns
    end    
  
  // Execute input and processing at positive edge of CLK
  always @(posedge CLK)
    begin
      RST <= 0;

      counter <= counter + 1;
      
      // Add a delay before the displays
      // Cause the bits won't reach the module in time
      // Brrrrrr
      $display("============================");
      $display("ADD = %d", ADD);
      $display("OUT = %b or %d", OUT, OUT);
      $display("COUNTADD = %d", COUNTADD);    
      
      // When CLR signal received, RST is triggered
      if (CLR == 0)
        begin
          RST <= 1;
        end
      
      // When counter exceeds 4, change Address to 6 
      // Demonstrates the module's ability to not process inputs...
      // ...before counter reset
      if (counter > 4)
        begin
          ADD <= 6;
        end
      
      // After 5 input entries, end simulation
      if (counter == 20)
        begin
          $finish;
        end
    end
endmodule

MemoryRead_v2.0/dump.vcd
$date
	Thu Jun 24 15:41:08 2021
$end
$version
	Icarus Verilog
$end
$timescale
	10ps
$end
$scope module tb $end
$var wire 1 ! CLR $end
$var wire 6 " COUNTADD [5:0] $end
$var wire 6 # OUT [5:0] $end
$var reg 6 $ ADD [5:0] $end
$var reg 1 % CLK $end
$var reg 1 & RST $end
$var integer 32 ' counter [31:0] $end
$upscope $end
$enddefinitions $end
#0
$dumpvars
b0 '
0&
1%
b101 $
b111111 #
b0 "
1!
$end
#2000
0%
#4000
b1 '
b1 "
1%
#6000
0%
#8000
b10 "
b10 '
1%
#10000
0%
#12000
b11 '
b11 "
1%
#14000
0%
#16000
b100 "
b100 '
1%
#18000
0%
#20000
b101 '
b101 "
1%
#22000
0%
#24000
0!
b101 #
b110 "
b110 $
b110 '
1%
#26000
0%
#28000
1&
b111 '
b111 "
b111111 #
1!
1%
#30000
0%
#32000
b0 "
b1000 '
0&
1%
#34000
0%
#36000
b1001 '
b1 "
1%
#38000
0%
#40000
b10 "
b1010 '
1%
#42000
0%
#44000
b1011 '
b11 "
1%
#46000
0%
#48000
b100 "
b1100 '
1%
#50000
0%
#52000
b1101 '
b101 "
1%
#54000
0%
#56000
b110 "
b1110 '
1%
#58000
0%
#60000
b1111 '
b111 "
0!
b110 #
1%
#62000
0%
#64000
b111111 #
1!
b1000 "
1&
b10000 '
1%
#66000
0%
#68000
b10001 '
0&
b0 "
1%
#70000
0%
#72000
b1 "
b10010 '
1%
#74000
0%
#76000
b10011 '
b10 "
1%
#78000
0%
#80000
b11 "
b10100 '
1%
#82000
0%
#84000
b10101 '
b100 "
1%
