FullMemoryWithCLK/design.sv
// Code your design here
// Code your design here
module counter(
  input CLK,
  input RST,
  output reg [5:0] count
);
  
  always @ (posedge CLK)
    begin
      if (RST == 1)
        begin
          count <= 0;
        end
      else if (RST == 0)
        begin
          count <= count + 1;
        end
    end
endmodule

module memory(CLK, RST, addr, data_in, RW_, CS, data_out);
  input CLK;
  input RST;
  input [5:0] addr;
  input [14:0] data_in;
  input RW_, CS;	//ReadWrite and Chip Select
  output reg [14:0] data_out;
  
  // Address Space in Chip = 64 pages
  // Data Space in a Cell = 12 bits
  reg [14:0] ram[63:0];
  wire [5:0] countADD;
  
  integer i;
  
  counter count0(CLK, RST, countADD);

  // Initialise memory with zeros
  initial begin
    for (i = 0; i < 64; i = i+ 1) begin
      ram[i[5:0]] <= 0;
    end
  end
  
  always @(posedge CLK) 
    begin
      if (CS == 0) 	// If CS is LOW, return high impedance
        begin
          data_out <= 15'bz;
        end
      else if (CS == 1)
        begin
          if (RW_ == 1)		//RW High means Read 
            begin
              if (countADD[5:0] == addr[5:0])
                data_out <= ram[addr[5:0]];
            end
          else if (RW_ == 0)	// RW Low means Write
            begin
              ram[addr[5:0]] <= data_in;
            end
        end
    end
endmodule

FullMemoryWithCLK/testbench.sv
// Code your testbench here
// or browse Examples

`timescale 1 ns/10 ps  // time-unit = 1 ns, precision = 10 ps

module tb();
  integer counter;
  reg CLK;
  reg RST;
  reg [5:0] ADD;
  reg [14:0] DATAIN;
  reg RW;
  reg CS;
  wire [5:0] COUNTADD;
  wire [14:0] DATAOUT;
  
  memory memory0(CLK, RST, ADD, DATAIN, RW, CS, DATAOUT);
  counter count0(CLK, RST, COUNTADD);
  
  // Initialise Registers
  initial begin
    //creating a file to store simulation waveform data
    $dumpfile("dump.vcd");
    //dump the waveform data to the file
    $dumpvars(1, tb);
    
    // Counter to determine simulation stop
    counter = -1;
    // Initialise Clock as 0 (LOW signal)
    CLK = 1'b0;
    
    // Blip the RST register
    RST <= 1;
    
    ADD <= 6'b111111;
    DATAIN <= 15'b111111111111111;
    
    RW = 0;
    CS = 1; 
  end

  // Runs indefinitely
  always
    begin
      // Pulsing of CLK
      CLK = 1'b1; 
      #20; // high for 20 * timescale = 20 ns

      CLK = 1'b0;
      #20; // low for 20 * timescale = 20 ns
    end    
  
  // Execute input and processing at positive edge of CLK
  always @(posedge CLK)
    begin
      
      if (counter == -1)
        RST <= 0;
      counter <= counter + 1;
      
      if (counter < 64)
        begin
          RW <= 0;
          ADD <= ADD + 1;
          DATAIN <= DATAIN + 1;
        end
      else if (counter > 63)
        begin
          RW <= 1;
          ADD <= 5;
        end
      
      if (counter > 127)
        $finish;
      
      $display("============================");
      $display("ADD = %b", ADD);
      $display("RW = %b", RW);
      $display("CS = %b", CS);
      $display("DATAIN = %b", DATAIN);
      $display("COUNTADD = %b", COUNTADD);
      $display("DATAOUT = %b", DATAOUT);
      
    end
endmodule

FullMemoryWithCLK/dump.vcd
$date
	Tue Sep  7 12:07:55 2021
$end
$version
	Icarus Verilog
$end
$timescale
	10ps
$end
$scope module tb $end
$var wire 6 ! COUNTADD [5:0] $end
$var wire 15 " DATAOUT [14:0] $end
$var reg 6 # ADD [5:0] $end
$var reg 1 $ CLK $end
$var reg 1 % CS $end
$var reg 15 & DATAIN [14:0] $end
$var reg 1 ' RST $end
$var reg 1 ( RW $end
$var integer 32 ) counter [31:0] $end
$upscope $end
$enddefinitions $end
#0
$dumpvars
b11111111111111111111111111111111 )
0(
1'
b111111111111111 &
1%
1$
b111111 #
bx "
bx !
$end
#2000
0$
#4000
b0 &
b0 #
b0 )
0'
b0 !
1$
#6000
0$
#8000
b1 !
b1 &
b1 #
b1 )
1$
#10000
0$
#12000
b10 &
b10 #
b10 )
b10 !
1$
#14000
0$
#16000
b11 !
b11 &
b11 #
b11 )
1$
#18000
0$
#20000
b100 &
b100 #
b100 )
b100 !
1$
#22000
0$
#24000
b101 !
b101 &
b101 #
b101 )
1$
#26000
0$
#28000
b110 &
b110 #
b110 )
b110 !
1$
#30000
0$
#32000
b111 !
b111 &
b111 #
b111 )
1$
#34000
0$
#36000
b1000 &
b1000 #
b1000 )
b1000 !
1$
#38000
0$
#40000
b1001 !
b1001 &
b1001 #
b1001 )
1$
#42000
0$
#44000
b1010 &
b1010 #
b1010 )
b1010 !
1$
#46000
0$
#48000
b1011 !
b1011 &
b1011 #
b1011 )
1$
#50000
0$
#52000
b1100 &
b1100 #
b1100 )
b1100 !
1$
#54000
0$
#56000
b1101 !
b1101 &
b1101 #
b1101 )
1$
#58000
0$
#60000
b1110 &
b1110 #
b1110 )
b1110 !
1$
#62000
0$
#64000
b1111 !
b1111 &
b1111 #
b1111 )
1$
#66000
0$
#68000
b10000 &
b10000 #
b10000 )
b10000 !
1$
#70000
0$
#72000
b10001 !
b10001 &
b10001 #
b10001 )
1$
#74000
0$
#76000
b10010 &
b10010 #
b10010 )
b10010 !
1$
#78000
0$
#80000
b10011 !
b10011 &
b10011 #
b10011 )
1$
#82000
0$
#84000
b10100 &
b10100 #
b10100 )
b10100 !
1$
#86000
0$
#88000
b10101 !
b10101 &
b10101 #
b10101 )
1$
#90000
0$
#92000
b10110 &
b10110 #
b10110 )
b10110 !
1$
#94000
0$
#96000
b10111 !
b10111 &
b10111 #
b10111 )
1$
#98000
0$
#100000
b11000 &
b11000 #
b11000 )
b11000 !
1$
#102000
0$
#104000
b11001 !
b11001 &
b11001 #
b11001 )
1$
#106000
0$
#108000
b11010 &
b11010 #
b11010 )
b11010 !
1$
#110000
0$
#112000
b11011 !
b11011 &
b11011 #
b11011 )
1$
#114000
0$
#116000
b11100 &
b11100 #
b11100 )
b11100 !
1$
#118000
0$
#120000
b11101 !
b11101 &
b11101 #
b11101 )
1$
#122000
0$
#124000
b11110 &
b11110 #
b11110 )
b11110 !
1$
#126000
0$
#128000
b11111 !
b11111 &
b11111 #
b11111 )
1$
#130000
0$
#132000
b100000 &
b100000 #
b100000 )
b100000 !
1$
#134000
0$
#136000
b100001 !
b100001 &
b100001 #
b100001 )
1$
#138000
0$
#140000
b100010 &
b100010 #
b100010 )
b100010 !
1$
#142000
0$
#144000
b100011 !
b100011 &
b100011 #
b100011 )
1$
#146000
0$
#148000
b100100 &
b100100 #
b100100 )
b100100 !
1$
#150000
0$
#152000
b100101 !
b100101 &
b100101 #
b100101 )
1$
#154000
0$
#156000
b100110 &
b100110 #
b100110 )
b100110 !
1$
#158000
0$
#160000
b100111 !
b100111 &
b100111 #
b100111 )
1$
#162000
0$
#164000
b101000 &
b101000 #
b101000 )
b101000 !
1$
#166000
0$
#168000
b101001 !
b101001 &
b101001 #
b101001 )
1$
#170000
0$
#172000
b101010 &
b101010 #
b101010 )
b101010 !
1$
#174000
0$
#176000
b101011 !
b101011 &
b101011 #
b101011 )
1$
#178000
0$
#180000
b101100 &
b101100 #
b101100 )
b101100 !
1$
#182000
0$
#184000
b101101 !
b101101 &
b101101 #
b101101 )
1$
#186000
0$
#188000
b101110 &
b101110 #
b101110 )
b101110 !
1$
#190000
0$
#192000
b101111 !
b101111 &
b101111 #
b101111 )
1$
#194000
0$
#196000
b110000 &
b110000 #
b110000 )
b110000 !
1$
#198000
0$
#200000
b110001 !
b110001 &
b110001 #
b110001 )
1$
#202000
0$
#204000
b110010 &
b110010 #
b110010 )
b110010 !
1$
#206000
0$
#208000
b110011 !
b110011 &
b110011 #
b110011 )
1$
#210000
0$
#212000
b110100 &
b110100 #
b110100 )
b110100 !
1$
#214000
0$
#216000
b110101 !
b110101 &
b110101 #
b110101 )
1$
#218000
0$
#220000
b110110 &
b110110 #
b110110 )
b110110 !
1$
#222000
0$
#224000
b110111 !
b110111 &
b110111 #
b110111 )
1$
#226000
0$
#228000
b111000 &
b111000 #
b111000 )
b111000 !
1$
#230000
0$
#232000
b111001 !
b111001 &
b111001 #
b111001 )
1$
#234000
0$
#236000
b111010 &
b111010 #
b111010 )
b111010 !
1$
#238000
0$
#240000
b111011 !
b111011 &
b111011 #
b111011 )
1$
#242000
0$
#244000
b111100 &
b111100 #
b111100 )
b111100 !
1$
#246000
0$
#248000
b111101 !
b111101 &
b111101 #
b111101 )
1$
#250000
0$
#252000
b111110 &
b111110 #
b111110 )
b111110 !
1$
#254000
0$
#256000
b111111 !
b111111 &
b111111 #
b111111 )
1$
#258000
0$
#260000
b1000000 &
b0 #
b1000000 )
b0 !
1$
#262000
0$
#264000
b1 !
b101 #
1(
b1000001 )
1$
#266000
0$
#268000
b1000010 )
b10 !
1$
#270000
0$
#272000
b11 !
b1000011 )
1$
#274000
0$
#276000
b1000100 )
b100 !
1$
#278000
0$
#280000
b101 !
b1000101 )
1$
#282000
0$
#284000
b1000110 )
b110 !
b101 "
1$
#286000
0$
#288000
b111 !
b1000111 )
1$
#290000
0$
#292000
b1001000 )
b1000 !
1$
#294000
0$
#296000
b1001 !
b1001001 )
1$
#298000
0$
#300000
b1001010 )
b1010 !
1$
#302000
0$
#304000
b1011 !
b1001011 )
1$
#306000
0$
#308000
b1001100 )
b1100 !
1$
#310000
0$
#312000
b1101 !
b1001101 )
1$
#314000
0$
#316000
b1001110 )
b1110 !
1$
#318000
0$
#320000
b1111 !
b1001111 )
1$
#322000
0$
#324000
b1010000 )
b10000 !
1$
#326000
0$
#328000
b10001 !
b1010001 )
1$
#330000
0$
#332000
b1010010 )
b10010 !
1$
#334000
0$
#336000
b10011 !
b1010011 )
1$
#338000
0$
#340000
b1010100 )
b10100 !
1$
#342000
0$
#344000
b10101 !
b1010101 )
1$
#346000
0$
#348000
b1010110 )
b10110 !
1$
#350000
0$
#352000
b10111 !
b1010111 )
1$
#354000
0$
#356000
b1011000 )
b11000 !
1$
#358000
0$
#360000
b11001 !
b1011001 )
1$
#362000
0$
#364000
b1011010 )
b11010 !
1$
#366000
0$
#368000
b11011 !
b1011011 )
1$
#370000
0$
#372000
b1011100 )
b11100 !
1$
#374000
0$
#376000
b11101 !
b1011101 )
1$
#378000
0$
#380000
b1011110 )
b11110 !
1$
#382000
0$
#384000
b11111 !
b1011111 )
1$
#386000
0$
#388000
b1100000 )
b100000 !
1$
#390000
0$
#392000
b100001 !
b1100001 )
1$
#394000
0$
#396000
b1100010 )
b100010 !
1$
#398000
0$
#400000
b100011 !
b1100011 )
1$
#402000
0$
#404000
b1100100 )
b100100 !
1$
#406000
0$
#408000
b100101 !
b1100101 )
1$
#410000
0$
#412000
b1100110 )
b100110 !
1$
#414000
0$
#416000
b100111 !
b1100111 )
1$
#418000
0$
#420000
b1101000 )
b101000 !
1$
#422000
0$
#424000
b101001 !
b1101001 )
1$
#426000
0$
#428000
b1101010 )
b101010 !
1$
#430000
0$
#432000
b101011 !
b1101011 )
1$
#434000
0$
#436000
b1101100 )
b101100 !
1$
#438000
0$
#440000
b101101 !
b1101101 )
1$
#442000
0$
#444000
b1101110 )
b101110 !
1$
#446000
0$
#448000
b101111 !
b1101111 )
1$
#450000
0$
#452000
b1110000 )
b110000 !
1$
#454000
0$
#456000
b110001 !
b1110001 )
1$
#458000
0$
#460000
b1110010 )
b110010 !
1$
#462000
0$
#464000
b110011 !
b1110011 )
1$
#466000
0$
#468000
b1110100 )
b110100 !
1$
#470000
0$
#472000
b110101 !
b1110101 )
1$
#474000
0$
#476000
b1110110 )
b110110 !
1$
#478000
0$
#480000
b110111 !
b1110111 )
1$
#482000
0$
#484000
b1111000 )
b111000 !
1$
#486000
0$
#488000
b111001 !
b1111001 )
1$
#490000
0$
#492000
b1111010 )
b111010 !
1$
#494000
0$
#496000
b111011 !
b1111011 )
1$
#498000
0$
#500000
b1111100 )
b111100 !
1$
#502000
0$
#504000
b111101 !
b1111101 )
1$
#506000
0$
#508000
b1111110 )
b111110 !
1$
#510000
0$
#512000
b111111 !
b1111111 )
1$
#514000
0$
#516000
b10000000 )
b0 !
1$
#518000
0$
#520000
b1 !
b10000001 )
1$
