AlphabetRankingBlock_v1.0/design.sv
// 6-bit RST Counter
module counter(
  input CLK,
  input RST,
  output reg [5:0] count
);
  
  always @ (posedge CLK)
    begin
      if (RST == 1)
        begin
          count <= 0;
        end
      else if (RST == 0)
        begin
          count <= count + 1;
        end
    end
  
endmodule

// Single Full Subtractor
module full_sub(
  input X,
  input Y,
  input Bin,
  output DIFF,
  output Bout
);
  
  wire X1;
  wire X2;
  wire X3;
  
  xor(X1, X, Y);
  and(X2, ~X, Y);
  and(X3, ~X1, Bin);
  xor(DIFF, X1, Bin);
  or(Bout, X3, X2);
  
endmodule

// NEED TO CHANGE TO 15 BITS
// 12-bit Full Subtractor
module full_sub12(
  input [11:0] X, Y,
  input Bin,
  output [11:0] DIFF,
  output Bout);
  
  wire [10:0] borrow;
  
  // Applying single full-subtractors to implement 12-bit subtractor
  full_sub fs0(
    .X(X[0]),
    .Y(Y[0]),
    .Bin(Bin),
    .DIFF(DIFF[0]),
    .Bout(borrow[0])
  );
  
  full_sub fs1(
    .X(X[1]),
    .Y(Y[1]),
    .Bin(borrow[0]),
    .DIFF(DIFF[1]),
    .Bout(borrow[1])
  );
  
  full_sub fs2(
    .X(X[2]),
    .Y(Y[2]),
    .Bin(borrow[1]),
    .DIFF(DIFF[2]),
    .Bout(borrow[2])
  );
  
  full_sub fs3(
    .X(X[3]),
    .Y(Y[3]),
    .Bin(borrow[2]),
    .DIFF(DIFF[3]),
    .Bout(borrow[3])
  );
  
  full_sub fs4(
    .X(X[4]),
    .Y(Y[4]),
    .Bin(borrow[3]),
    .DIFF(DIFF[4]),
    .Bout(borrow[4])
  );
  
  full_sub fs5(
    .X(X[5]),
    .Y(Y[5]),
    .Bin(borrow[4]),
    .DIFF(DIFF[5]),
    .Bout(borrow[5])
  );
  
  full_sub fs6(
    .X(X[6]),
    .Y(Y[6]),
    .Bin(borrow[5]),
    .DIFF(DIFF[6]),
    .Bout(borrow[6])
  );
  
  full_sub fs7(
    .X(X[7]),
    .Y(Y[7]),
    .Bin(borrow[6]),
    .DIFF(DIFF[7]),
    .Bout(borrow[7])
  );
  
  full_sub fs8(
    .X(X[8]),
    .Y(Y[8]),
    .Bin(borrow[7]),
    .DIFF(DIFF[8]),
    .Bout(borrow[8])
  );
  
  full_sub fs9(
    .X(X[9]),
    .Y(Y[9]),
    .Bin(borrow[8]),
    .DIFF(DIFF[9]),
    .Bout(borrow[9])
  );
  
  full_sub fs10(
    .X(X[10]),
    .Y(Y[10]),
    .Bin(borrow[9]),
    .DIFF(DIFF[10]),
    .Bout(borrow[10])
  );
  
  full_sub fs11(
    .X(X[11]),
    .Y(Y[11]),
    .Bin(borrow[10]),
    .DIFF(DIFF[11]),
    .Bout(Bout)
  ); 
  
endmodule 

// Cache Memory for Accelerator
module memory(CLK, addr, data_in, RW_, CS, data_out, addr_out);
  input CLK;
  input [5:0] addr;
  // NEED TO CHANGE TO 15 BITS
  input [11:0] data_in;
  input RW_, CS;	//ReadWrite, Chip Select
  // NEED TO CHANGE TO 15 BITS
  output reg [11:0] data_out;
  output reg [5:0] addr_out;
  
  // Address Space in Chip = 64 pages
  // Data Space in a Cell = 12 bits
  // NEED TO CHANGE TO 15 BITS
  reg [11:0] ram[63:0];
  // NEED TO CHANGE TO 15 BITS
  reg [11:0] min;
  reg [5:0] smallest_addr;  
  
  integer i;

  // Initialise memory with Z values
  initial begin
    for (i = 0; i < 64; i = i+ 1) begin
      // NEED TO CHANGE TO 15 BITS
      ram[i[5:0]] <= 12'bz;
    end
    
    min <= 63;
  end
  
  always @(posedge CLK) 
    begin
      if (CS == 0) 	// If CS is LOW, return high impedance
        begin
          // NEED TO CHANGE TO 15 BITS
          data_out <= 12'bz;
        end
      else if (CS == 1)
        begin
          if (RW_ == 1)		//RW High means Read 
            begin
              // Sorting starts here
              for (i = 0; i < 64; i = i+ 1) 
                begin
                  if (ram[i[5:0]] < min)
                    begin
                      min <= ram[i[5:0]];
                      smallest_addr <= i;
                    end
                end
              
              addr_out <= smallest_addr;
              // Output the address (alphabet)
              data_out <= ram[addr[5:0]];
            end
          else if (RW_ == 0)	// RW Low means Write
            begin
              ram[addr[5:0]] <= data_in;
            end
        end
    end
endmodule

// Subtractor submodule
module subtractor_module(
  input CLK,
  input DE,
  // NEED TO CHANGE TO 15 BITS
  input [11:0] SENSOR_IN,
  // NEED TO CHANGE TO 15 BITS
  input [11:0] REF,
  input BIN,
  output reg OE,
  // NEED TO CHANGE TO 15 BITS
  output reg [11:0] NEW_OUT,
  output BOUT
);
  
  wire [5:0] count;
  // NEED TO CHANGE TO 15 BITS
  wire [11:0] OUT;
  
  full_sub12 fs12_0(SENSOR_IN, REF, BIN, OUT, BOUT);
  
  always @(posedge CLK)
    begin
      if (DE == 1)
        begin
          // NEED TO CHANGE TO 15 BITS
          NEW_OUT <= 12'bz;
          OE <= 1;
        end
      else if (DE == 0)
        begin
          if (BOUT == 1)
            begin
              NEW_OUT <= ~OUT + 1'b1;
              OE <= 0;
            end
          else if (BOUT == 0)
            begin
              NEW_OUT <= OUT;
              OE <= 0;
            end
        end
    end
endmodule

module sorting(CLK, addr_in, data_in, RW_, CS, addr_out);
  input CLK;
  input [5:0] addr_in;
  // NEED TO CHANGE TO 15 BITS
  input [11:0] data_in;
  input RW_, CS;	//ReadWrite, Chip Select
  output reg [5:0] addr_out;
  
  // NEED TO CHANGE TO 15 BITS
  reg [11:0] ram[63:0];
  
  always @(posedge CLK)
    begin
      ram[addr_in[5:0]] <= data_in;
    end
  
endmodule

AlphabetRankingBlock_v1.0/testbench.sv
// Code your testbench here
// or browse Examples

`timescale 1 ns/10 ps  // time-unit = 1 ns, precision = 10 ps

module tb();
  reg CLK;
  
  reg RST;
  reg [5:0] buffer_outcount_0;
  reg [5:0] buffer_outcount_1;
  wire [5:0] out_count;
  
  reg DE;
  reg BUFFER_DE;
  // NEED TO CHANGE TO 15 BITS
  reg [11:0] X;
  // NEED TO CHANGE TO 15 BITS
  reg [11:0] Y;
  reg Bin;
  wire OE;
  // NEED TO CHANGE TO 15 BITS
  wire [11:0] DIFF;
  wire Bout;
  
  reg RW_;
  reg CS;
  // NEED TO CHANGE TO 15 BITS
  reg [11:0] BUFFER_DIFF;
  // NEED TO CHANGE TO 15 BITS
  wire [11:0] DIFF_OUT;
  
  wire [5:0] addr_out;
  
  integer counter;
  
  counter co0(CLK, RST, out_count);
  subtractor_module sm(CLK, DE, X, Y, Bin, OE, DIFF, Bout);
  memory mem(CLK, buffer_outcount_1, BUFFER_DIFF, RW_, CS, DIFF_OUT, addr_out);
  
  // Initialise Registers
  initial begin
    //creating a file to store simulation waveform data
    $dumpfile("dump.vcd");
    //dump the waveform data to the file
    $dumpvars(1, tb);
    
    // Counter to determine simulation stop
    counter = 0;
    // Initialise Clock as 0 (LOW signal)
    CLK = 1'b0;
    
    RST <= 1;
    
    X <= 0;
    Y <= 0;
    DE <= 1;
    Bin <= 0;
    
    CS <= 0;
  end

  // Runs indefinitely
  always
    begin
      // Pulsing of CLK
      CLK = 1'b1; 
      #20; // high for 20 * timescale = 20 ns

      CLK = 1'b0;
      #20; // low for 20 * timescale = 20 ns
    end    
  
  // Execute input and processing at positive edge of CLK
  always @(posedge CLK)
    begin
      buffer_outcount_0 <= out_count;
      buffer_outcount_1 <= buffer_outcount_0;
      
      BUFFER_DE <= DE;
      BUFFER_DIFF <= DIFF;
      RST <= 0;
      
      RW_ <= OE;
      
      counter <= counter + 1;
      
      if (counter < 5)
        begin
          DE <= 0;
          X <= $urandom%63;
          Y <= $urandom%63;
          if (counter == 4)
            begin
              X <= 2;
              Y <= 1;
            end
          if (OE == 0)
            begin
              CS <= 1;
            end
        end
      
      $display("============================");
      $display("X = %d", X);
      $display("Y = %d", Y);
      $display("DIFF = %d", DIFF);
      $display("OE = %d", OE);
      
      // I need a way to trigger DE -> 1 
      // Rather than using time-based
      // Maybe some way to detect no-more-input?
      if (counter == 5)
        begin
          RST <= 1;
          DE <= 1;
        end
      
      // After 20 input entries, end simulation
      if (counter == 20)
        begin
          $finish;
        end
    end
endmodule

AlphabetRankingBlock_v1.0/dump.vcd
$date
	Tue Sep  7 12:13:46 2021
$end
$version
	Icarus Verilog
$end
$timescale
	10ps
$end
$scope module tb $end
$var wire 1 ! Bout $end
$var wire 12 " DIFF [11:0] $end
$var wire 12 # DIFF_OUT [11:0] $end
$var wire 1 $ OE $end
$var wire 6 % addr_out [5:0] $end
$var wire 6 & out_count [5:0] $end
$var reg 1 ' BUFFER_DE $end
$var reg 12 ( BUFFER_DIFF [11:0] $end
$var reg 1 ) Bin $end
$var reg 1 * CLK $end
$var reg 1 + CS $end
$var reg 1 , DE $end
$var reg 1 - RST $end
$var reg 1 . RW_ $end
$var reg 12 / X [11:0] $end
$var reg 12 0 Y [11:0] $end
$var reg 6 1 buffer_outcount_0 [5:0] $end
$var reg 6 2 buffer_outcount_1 [5:0] $end
$var integer 32 3 counter [31:0] $end
$upscope $end
$enddefinitions $end
#0
$dumpvars
b0 3
bx 2
bx 1
b0 0
b0 /
x.
1-
1,
0+
1*
0)
bx (
x'
bx &
bx %
x$
bx #
bx "
0!
$end
#2000
0*
#4000
1!
b110100 0
b100101 /
0,
b1 3
0-
1'
bz #
1$
bz "
b0 &
1*
#6000
0*
#8000
b1 &
0$
b1111 "
b110000 0
b10100 /
b10 3
1.
bz (
0'
b0 1
1*
#10000
0*
#12000
1+
b101110 0
b1000 /
b11 3
0.
b1111 (
b0 2
b1 1
b11100 "
b10 &
1*
#14000
0*
#16000
b11 &
b100110 "
b100110 0
b11 /
b100 3
b11100 (
b1 2
b10 1
1*
#18000
0*
#20000
0!
b1 0
b10 /
b101 3
b100110 (
b10 2
b11 1
b100011 "
b100 &
1*
#22000
0*
#24000
b101 &
b1 "
1,
1-
b110 3
b100011 (
b11 2
b100 1
1*
#26000
0*
#28000
b111 3
0-
b1 (
1'
b100 2
b101 1
1$
bz "
b0 &
1*
#30000
0*
#32000
b1 &
b1000 3
1.
bz (
b101 2
b0 1
1*
#34000
0*
#36000
b1001 3
b0 2
b1 1
b10 &
1*
#38000
0*
#40000
b11 &
b1111 #
b100 %
b1010 3
b1 2
b10 1
1*
#42000
0*
#44000
b1011 3
b10 2
b11 1
b11100 #
b100 &
1*
#46000
0*
#48000
b101 &
b100110 #
b1100 3
b11 2
b100 1
1*
#50000
0*
#52000
b1101 3
b100 2
b101 1
b100011 #
b110 &
1*
#54000
0*
#56000
b111 &
b1 #
b1110 3
b101 2
b110 1
1*
#58000
0*
#60000
b1111 3
b110 2
b111 1
bz #
b1000 &
1*
#62000
0*
#64000
b1001 &
b10000 3
b111 2
b1000 1
1*
#66000
0*
#68000
b10001 3
b1000 2
b1001 1
b1010 &
1*
#70000
0*
#72000
b1011 &
b10010 3
b1001 2
b1010 1
1*
#74000
0*
#76000
b10011 3
b1010 2
b1011 1
b1100 &
1*
#78000
0*
#80000
b1101 &
b10100 3
b1011 2
b1100 1
1*
#82000
0*
#84000
b10101 3
b1100 2
b1101 1
b1110 &
1*
